telma/__init__.py
telma/telma.py
telma-1.0.6.dist-info/METADATA
telma-1.0.6.dist-info/WHEEL
telma-1.0.6.dist-info/top_level.txt
telma-1.0.6.dist-info/RECORD
